rajgolepu/__init__.py
rajgolepu/cli.py
rajgolepu/utils.py
rajgolepu-0.1.2.dist-info/licenses/LICENSE
rajgolepu-0.1.2.dist-info/METADATA
rajgolepu-0.1.2.dist-info/WHEEL
rajgolepu-0.1.2.dist-info/entry_points.txt
rajgolepu-0.1.2.dist-info/top_level.txt
rajgolepu-0.1.2.dist-info/RECORD
