Metadata-Version: 2.4
Name: rajgolepu
Version: 0.1.2
Summary: Raj Golepu's personal Python package and CLI tool.
Author-email: Raj Golepu <raj@example.com>
License: MIT License
Project-URL: Homepage, https://github.com/rajgolepu
Classifier: Programming Language :: Python :: 3
Classifier: License :: OSI Approved :: MIT License
Classifier: Operating System :: OS Independent
Classifier: Development Status :: 4 - Beta
Classifier: Intended Audience :: Developers
Requires-Python: >=3.7
License-File: LICENSE
Dynamic: license-file
